pictory/__init__.py
pictory/pictory.py
pictory-0.1.0.dist-info/LICENSE
pictory-0.1.0.dist-info/METADATA
pictory-0.1.0.dist-info/WHEEL
pictory-0.1.0.dist-info/entry_points.txt
pictory-0.1.0.dist-info/top_level.txt
pictory-0.1.0.dist-info/RECORD
