Metadata-Version: 2.1
Name: pictory
Version: 0.1.0
Summary: simple tool to organize pictures and videos in lickable directories
Home-page: https://github.com/ramonsaraiva/pictory
Author: Ramon Saraiva
Author-email: ramonsaraiva@gmail.com
License: MIT
Platform: UNKNOWN
Classifier: Development Status :: 3 - Alpha
Classifier: License :: OSI Approved :: MIT License
Classifier: Natural Language :: English
Classifier: Operating System :: OS Independent
Classifier: Programming Language :: Python :: 3
Classifier: Programming Language :: Python :: 3.7
Classifier: Topic :: Utilities
